nodeconductor_sugarcrm/__init__.py
nodeconductor_sugarcrm/admin.py
nodeconductor_sugarcrm/apps.py
nodeconductor_sugarcrm/backend.py
nodeconductor_sugarcrm/cost_tracking.py
nodeconductor_sugarcrm/extension.py
nodeconductor_sugarcrm/handlers.py
nodeconductor_sugarcrm/log.py
nodeconductor_sugarcrm/models.py
nodeconductor_sugarcrm/perms.py
nodeconductor_sugarcrm/serializers.py
nodeconductor_sugarcrm/signals.py
nodeconductor_sugarcrm/tasks.py
nodeconductor_sugarcrm/urls.py
nodeconductor_sugarcrm/utils.py
nodeconductor_sugarcrm/views.py
nodeconductor_sugarcrm/management/__init__.py
nodeconductor_sugarcrm/management/commands/__init__.py
nodeconductor_sugarcrm/management/commands/initcrminstanceurl.py
nodeconductor_sugarcrm/migrations/0001_squashed_0009_remove_crm_size_field.py
nodeconductor_sugarcrm/migrations/0010_crm_instance_url.py
nodeconductor_sugarcrm/migrations/0011_crm_publishing_state.py
nodeconductor_sugarcrm/migrations/0012_remove_spl_state.py
nodeconductor_sugarcrm/migrations/0013_remove_payable_mixin.py
nodeconductor_sugarcrm/migrations/__init__.py
nodeconductor_sugarcrm-0.5.0.dist-info/DESCRIPTION.rst
nodeconductor_sugarcrm-0.5.0.dist-info/METADATA
nodeconductor_sugarcrm-0.5.0.dist-info/RECORD
nodeconductor_sugarcrm-0.5.0.dist-info/WHEEL
nodeconductor_sugarcrm-0.5.0.dist-info/entry_points.txt
nodeconductor_sugarcrm-0.5.0.dist-info/metadata.json
nodeconductor_sugarcrm-0.5.0.dist-info/top_level.txt
