Metadata-Version: 2.0
Name: nodeconductor-sugarcrm
Version: 0.5.0
Summary: NodeConductor SugarCRM adds SugarCRM support to NodeConductor
Home-page: http://nodeconductor.com
Author: OpenNode Team
Author-email: info@opennodecloud.com
License: UNKNOWN
Platform: UNKNOWN
Classifier: Framework :: Django
Classifier: Intended Audience :: Developers
Classifier: Intended Audience :: System Administrators
Classifier: Operating System :: OS Independent
Classifier: License :: OSI Approved :: MIT License
Requires-Dist: nodeconductor (>0.108.0)
Requires-Dist: nodeconductor-openstack (>=0.4.1)
Requires-Dist: sugarcrm (>=0.1.1)
Provides-Extra: dev
Requires-Dist: Sphinx (==1.2.2); extra == 'dev'
